chaoswm/__init__.py
chaoswm/actions.py
chaoswm/driver.py
chaoswm/probes.py
chaoswm/utils.py
chaoswm-0.2.1.dist-info/LICENSE
chaoswm-0.2.1.dist-info/METADATA
chaoswm-0.2.1.dist-info/WHEEL
chaoswm-0.2.1.dist-info/top_level.txt
chaoswm-0.2.1.dist-info/RECORD
