Metadata-Version: 2.1
Name: chaoswm
Version: 0.2.1
Summary: chaostoolkit driver for wiremock
Home-page: https://github.com/sky-uk/chaostoolkit-wiremock
Author: Marco Masetti
Author-email: marco.masetti@sky.uk
License: Apache License, v2.0
Keywords: chaoswm
Platform: UNKNOWN
Classifier: Development Status :: 2 - Pre-Alpha
Classifier: Intended Audience :: Developers
Classifier: License :: OSI Approved :: BSD License
Classifier: Natural Language :: English
Classifier: Programming Language :: Python :: 3.5
Classifier: Programming Language :: Python :: 3.6
Classifier: Programming Language :: Python :: 3.7
Requires-Dist: chaostoolkit-lib (>=1.5.0)
Requires-Dist: typing
Requires-Dist: logzero
Requires-Dist: requests
